models/__init__.py
models/sourcesPattern.py
stack_spy-1.0.0.dist-info/licenses/LICENSE
stack_spy-1.0.0.dist-info/METADATA
stack_spy-1.0.0.dist-info/WHEEL
stack_spy-1.0.0.dist-info/top_level.txt
stack_spy-1.0.0.dist-info/RECORD
