Metadata-Version: 2.4
Name: stack_spy
Version: 1.0.0
Summary: Stack analysis and discovery tool for webs.
Author-email: EssEnemiGz <biscenfabian@gmail.com>
License-File: LICENSE
Requires-Dist: aiohttp
Dynamic: license-file
